{
  "keyBassSoftStep": 0,
  "keySoftMuteTimeStep": 0,
  "keySoftMutePin": 0,
  "keyLFSpeaker": 90,
  "keyMixLevelSubEnable": 0,
  "keySpectrumRun": 0,
  "keySpectrumSource": 0,
  "keyLoudnessValue": 0,
  "keyLoudnessSoftStep": 0,
  "keyMixLevelLFS": 0,
  "keySpectrumQFactor": 1,
  "keyBassValue": 14,
  "keyMainSourceGain": 15,
  "keyChipReset": 0,
  "keyMiddleValue": 0,
  "keyDataSecondSource": 0,
  "keyDataDriverSetup": 193,
  "keyDataLoudness": 0,
  "keySubSetupMiddleFreq": 0,
  "keyTrebleCenterFreq": 3,
  "keyDataTreble": 246,
  "keyMixLevelRFS": 0,
  "keyDataMixLevel": 0,
  "keyDataBass": 30,
  "keyChipClockSource": 0,
  "keySubSetupCutFreq": 0,
  "keySecondSourceValue": 0,
  "keyMiddleQFactor": 0,
  "keyDataSoftMute": 1,
  "keySoftMuteTime": 0,
  "keyChipResetMode": 0,
  "keyLoudnessBoost": 0,
  "keySubSetupDcMode": 0,
  "keyMixLevelValue": 0,
  "keySoftMuteValue": 1,
  "keyTrebleReferenceOutput": 1,
  "keySubVolume": 9,
  "keyLRSpeaker": 0,
  "keyTrebleValue": 6,
  "keyBassQFactor": 0,
  "keyDataMainSource": 120,
  "keyCouplingMode": 3,
  "keyRFSpeaker": 89,
  "general_config": null,
  "keySecondSourceRearSource": 0,
  "keySubSetupSmooth": 0,
  "keyRRSpeaker": 1,
  "keyGainEffectForDso": 0,
  "keySubSetupBassFreq": 0,
  "keyLoudnessFreq": 0,
  "keyMixGain": 9,
  "keyDataMiddle": 16,
  "keyMainSourceValue": 0,
  "keyMainVolume": 90,
  "keyMixLevelEnable": 0,
  "keyDataSubSetup": 0,
  "keyMiddleSoftStep": 0,
  "keyVolumesSoftStep": 0,
  "keySecondSourceGain": 0,
  "keySoftMuteEnable": 1
}